README.md
setup.py
srun/__init__.py
srun/common.py
srun/encrypt.py
srun/local.py
srun/shell.py
srun/status.py
srun_cli.egg-info/PKG-INFO
srun_cli.egg-info/SOURCES.txt
srun_cli.egg-info/dependency_links.txt
srun_cli.egg-info/entry_points.txt
srun_cli.egg-info/requires.txt
srun_cli.egg-info/top_level.txt