Metadata-Version: 1.0
Name: srun-cli
Version: 0.1.1
Summary: A Command line interface for Srun3k Client for HAUT
Home-page: https://github.com/CHN-STUDENT/srun-cli
Author: CHN-STUDENT
Author-email: chn-student@outlook.com
License: http://www.apache.org/licenses/LICENSE-2.0
Platform: UNKNOWN
